python_docs_theme_technopathy/__init__.py
python_docs_theme_technopathy/github.html
python_docs_theme_technopathy/layout.html
python_docs_theme_technopathy/searchbox.html
python_docs_theme_technopathy/theme.conf
python_docs_theme_technopathy/static/copybutton.js
python_docs_theme_technopathy/static/github-logo.png
python_docs_theme_technopathy/static/lucit.png
python_docs_theme_technopathy/static/py.png
python_docs_theme_technopathy/static/pydoctheme.css
python_docs_theme_technopathy/static/sidebar.js
python_docs_theme_technopathy-0.9.1.dist-info/LICENSE
python_docs_theme_technopathy-0.9.1.dist-info/METADATA
python_docs_theme_technopathy-0.9.1.dist-info/WHEEL
python_docs_theme_technopathy-0.9.1.dist-info/entry_points.txt
python_docs_theme_technopathy-0.9.1.dist-info/top_level.txt
python_docs_theme_technopathy-0.9.1.dist-info/RECORD
