Metadata-Version: 2.1
Name: python-docs-theme-technopathy
Version: 0.9.1
Summary: A responsive sphinx theme for github pages based on python-docs-theme
Home-page: https://www.lucit.tech
Author: Oliver Zehentleitner
Project-URL: Source, https://github.com/LUCIT-Systems-and-Development/python-docs-theme-technopathy
Project-URL: Howto, https://www.technopathy.club/2019/11/03/use-python-sphinx-on-github-pages-with-html-and-an-indivdual-template/
Project-URL: Author, https://www.lucit.tech
Classifier: Intended Audience :: Developers
Classifier: Development Status :: 5 - Production/Stable
Classifier: Framework :: Sphinx
Classifier: Framework :: Sphinx :: Theme
Classifier: License :: OSI Approved :: Python Software Foundation License
Classifier: Operating System :: OS Independent
Classifier: Topic :: Documentation
Classifier: Topic :: Software Development :: Documentation
Classifier: Programming Language :: Python :: 3
License-File: LICENSE
